CherryExport/CherryExport.py
CherryExport/__init__.py
CherryExport/resources/Docx.docx
CherryExport/resources/TextFile.txt
CherryExport-0.1.dist-info/METADATA
CherryExport-0.1.dist-info/WHEEL
CherryExport-0.1.dist-info/entry_points.txt
CherryExport-0.1.dist-info/top_level.txt
CherryExport-0.1.dist-info/RECORD
