Metadata-Version: 2.1
Name: CherryExport
Version: 0.1
Requires-Dist: python-docx
